<?xml version = '1.0' encoding = 'UTF-8'?>
<Relation class="oracle.dbtools.crest.model.design.logical.Relation" name="Relation_5" directorySegmentName="seg_0" id="C191A620-64C1-C911-7008-CC382038EED7">
<createdBy>macbook</createdBy>
<createdTime>2024-07-01 11:16:38 UTC</createdTime>
<ownerDesignName>Terminplaner_rel</ownerDesignName>
<engineerTo>
<item key="9D19A44B-4A44-D75E-17DC-7DC5AF33613C" value="true"/>
</engineerTo>
<sourcePk>4EC5B9F5-DF1D-FB4B-07AC-448FCB70B260</sourcePk>
<identifying>false</identifying>
<optionalSource>true</optionalSource>
<optionalTarget>false</optionalTarget>
<sourceCardinality>1</sourceCardinality>
<sourceEntity>CD6B90BC-2950-761C-2184-3598AC80D3C1</sourceEntity>
<targetCardinalityString>*</targetCardinalityString>
<targetEntity>969E8C73-4A7F-F49E-4A72-05FE6D002928</targetEntity>
<transferable>true</transferable>
<deleteRule>NO ACTION</deleteRule>
</Relation>